dexterity.localrolesfield-2.0.0b0-py3.13-nspkg.pth
dexterity/localrolesfield/__init__.py
dexterity/localrolesfield/adapter.py
dexterity/localrolesfield/configure.zcml
dexterity/localrolesfield/field.py
dexterity/localrolesfield/interfaces.py
dexterity/localrolesfield/subscriber.py
dexterity/localrolesfield/subscribers.zcml
dexterity/localrolesfield/testing.py
dexterity/localrolesfield/testing.zcml
dexterity/localrolesfield/utils.py
dexterity/localrolesfield/browser/__init__.py
dexterity/localrolesfield/browser/configure.zcml
dexterity/localrolesfield/browser/settings.py
dexterity/localrolesfield/locales/dexterity.localrolesfield-generated.pot
dexterity/localrolesfield/locales/dexterity.localrolesfield-manual.pot
dexterity/localrolesfield/locales/dexterity.localrolesfield.pot
dexterity/localrolesfield/locales/fr/LC_MESSAGES/dexterity.localrolesfield.po
dexterity/localrolesfield/profiles/default/browserlayer.xml
dexterity/localrolesfield/profiles/default/metadata.xml
dexterity/localrolesfield/profiles/testing/metadata.xml
dexterity/localrolesfield/profiles/testing/types.xml
dexterity/localrolesfield/profiles/testing/workflows.xml
dexterity/localrolesfield/profiles/testing/types/testingtype.xml
dexterity/localrolesfield/profiles/uninstall/browserlayer.xml
dexterity/localrolesfield/profiles/uninstall/metadata.xml
dexterity/localrolesfield/tests/__init__.py
dexterity/localrolesfield/tests/test_adapter.py
dexterity/localrolesfield/tests/test_robot.py
dexterity/localrolesfield/tests/test_setup.py
dexterity/localrolesfield/tests/test_subscriber.py
dexterity/localrolesfield/tests/robot/settings.robot
dexterity/localrolesfield/upgrades/__init__.py
dexterity/localrolesfield/upgrades/configure.zcml
dexterity/localrolesfield/upgrades/upgrades.py
dexterity_localrolesfield-2.0.0b0.dist-info/METADATA
dexterity_localrolesfield-2.0.0b0.dist-info/WHEEL
dexterity_localrolesfield-2.0.0b0.dist-info/namespace_packages.txt
dexterity_localrolesfield-2.0.0b0.dist-info/top_level.txt
dexterity_localrolesfield-2.0.0b0.dist-info/RECORD
