Metadata-Version: 2.4
Name: dexterity.localrolesfield
Version: 2.0.0b0
Summary: z3c.form local role field for dexterity
Home-page: https://github.com/collective/dexterity.localrolesfield
Author: IMIO
Author-email: support@imio.be
License: gpl
Project-URL: PyPI, https://pypi.python.org/pypi/dexterity.localrolesfield
Project-URL: Source, https://github.com/collective/dexterity.localrolesfield
Keywords: Plone Python
Classifier: Environment :: Web Environment
Classifier: Framework :: Plone
Classifier: Framework :: Plone :: 4.3
Classifier: Framework :: Plone :: 6.0
Classifier: Framework :: Plone :: 6.1
Classifier: Operating System :: OS Independent
Classifier: Programming Language :: Python
Classifier: Programming Language :: Python :: 2.7
Classifier: Programming Language :: Python :: 3.10
Classifier: Programming Language :: Python :: 3.13
Classifier: Topic :: Software Development :: Libraries :: Python Modules
Requires-Dist: Products.CMFCore
Requires-Dist: collective.z3cform.datagridfield
Requires-Dist: dexterity.localroles>=2.0.0.dev0
Requires-Dist: plone.api
Requires-Dist: plone.app.dexterity
Requires-Dist: setuptools
Requires-Dist: z3c.unconfigure
Provides-Extra: test
Requires-Dist: plone.api; extra == "test"
Requires-Dist: plone.app.testing; extra == "test"
Requires-Dist: plone.app.robotframework; extra == "test"
Dynamic: author
Dynamic: author-email
Dynamic: classifier
Dynamic: description
Dynamic: home-page
Dynamic: keywords
Dynamic: license
Dynamic: project-url
Dynamic: provides-extra
Dynamic: requires-dist
Dynamic: summary
